foundrytools_cli/__init__.py
foundrytools_cli/__main__.py
foundrytools_cli/commands/__init__.py
foundrytools_cli/commands/cff.py
foundrytools_cli/commands/cmap.py
foundrytools_cli/commands/converter/__init__.py
foundrytools_cli/commands/converter/cli.py
foundrytools_cli/commands/converter/ttf_to_otf.py
foundrytools_cli/commands/fix/__init__.py
foundrytools_cli/commands/fix/cli.py
foundrytools_cli/commands/fix/legacy_accents.py
foundrytools_cli/commands/fix/vertical_metrics.py
foundrytools_cli/commands/font.py
foundrytools_cli/commands/gsub.py
foundrytools_cli/commands/hhea.py
foundrytools_cli/commands/name.py
foundrytools_cli/commands/os_2.py
foundrytools_cli/commands/otf.py
foundrytools_cli/commands/post.py
foundrytools_cli/commands/print/__init__.py
foundrytools_cli/commands/print/cli.py
foundrytools_cli/commands/print/font_info.py
foundrytools_cli/commands/print/font_names.py
foundrytools_cli/commands/print/vf_instances.py
foundrytools_cli/commands/ttf.py
foundrytools_cli/commands/utils/__init__.py
foundrytools_cli/commands/utils/cli.py
foundrytools_cli/commands/utils/font_organizer.py
foundrytools_cli/commands/utils/font_renamer.py
foundrytools_cli/commands/utils/sync_timestamps.py
foundrytools_cli/utils/__init__.py
foundrytools_cli/utils/logger.py
foundrytools_cli/utils/task_runner.py
foundrytools_cli/utils/timer.py
foundrytools_cli-2.1.1.dist-info/WHEEL
foundrytools_cli-2.1.1.dist-info/entry_points.txt
foundrytools_cli-2.1.1.dist-info/METADATA
foundrytools_cli-2.1.1.dist-info/RECORD
