Metadata-Version: 2.4
Name: foundrytools-cli
Version: 2.1.1
Summary: A set of command line tools to inspect, manipulate and convert font files
Author: Cesare Gilento
Author-email: Cesare Gilento <ftcli@proton.me>
License-Expression: MIT
Classifier: Development Status :: 5 - Production/Stable
Classifier: Intended Audience :: Developers
Classifier: Intended Audience :: End Users/Desktop
Classifier: Natural Language :: English
Classifier: Operating System :: OS Independent
Classifier: Programming Language :: Python :: 3
Classifier: Programming Language :: Python :: 3.10
Classifier: Programming Language :: Python :: 3.11
Classifier: Programming Language :: Python :: 3.12
Classifier: Programming Language :: Python :: 3.13
Classifier: Programming Language :: Python :: 3.14
Classifier: License :: OSI Approved :: MIT License
Classifier: Topic :: Text Processing :: Fonts
Requires-Dist: afdko>=4.0.3
Requires-Dist: click>=8.3.1
Requires-Dist: foundrytools>=0.1.6
Requires-Dist: loguru>=0.7.3
Requires-Dist: pathvalidate>=3.3.1
Requires-Dist: rich>=14.3.1
Requires-Dist: ufolib2>=0.18.1
Requires-Dist: win32-setctime>=1.2.0 ; sys_platform >= 'win32'
Requires-Python: >=3.10
Project-URL: Homepage, https://github.com/ftCLI/FoundryTools-CLI
